webint_live/__init__.py
webint_live/templates/__init__.py
webint_live/templates/chat.html
webint_live/templates/finished.sh
webint_live/templates/index.html
webint_live/templates/publish.sh
webint_live/templates/stream.html
webint_live-0.0.26.dist-info/METADATA
webint_live-0.0.26.dist-info/entry_points.txt
webint_live-0.0.26.dist-info/WHEEL
webint_live-0.0.26.dist-info/RECORD
